npica/__init__.py
npica/nonparametric_ica_python.py
npica-0.0.1.dist-info/LICENSE
npica-0.0.1.dist-info/METADATA
npica-0.0.1.dist-info/WHEEL
npica-0.0.1.dist-info/top_level.txt
npica-0.0.1.dist-info/RECORD
