Metadata-Version: 2.1
Name: npica
Version: 0.0.1
Summary: A Python implementation of https://github.com/snormanhaignere/nonparametric-ica
Home-page: https://github.com/dskrill/nonparametric-ica-python.git
Author: David Skrill
Author-email: davidmskrill@gmail.com
License: UNKNOWN
Project-URL: Bug Tracker, https://github.com/dskrill/nonparametric-ica-python/issues
Platform: UNKNOWN
Classifier: Programming Language :: Python :: 3
Classifier: License :: OSI Approved :: MIT License
Classifier: Operating System :: OS Independent
Requires-Python: >=3.6
License-File: LICENSE
